bank/__init__.py
bank/datamodel/__init__.py
bank/datamodel/v1/__init__.py
bank/datamodel/v1/dtos/__init__.py
bank/datamodel/v1/dtos/account.py
bank/datamodel/v1/dtos/balance.py
bank/datamodel/v1/dtos/createaccount.py
bank/datamodel/v1/dtos/createcustomer.py
bank/datamodel/v1/dtos/createtransfer.py
bank/datamodel/v1/dtos/customer.py
bank/datamodel/v1/dtos/error.py
bank/datamodel/v1/dtos/getaccount.py
bank/datamodel/v1/dtos/getaccountbalance.py
bank/datamodel/v1/dtos/getaccounttransfers.py
bank/datamodel/v1/dtos/getallaccounts.py
bank/datamodel/v1/dtos/getallcustomers.py
bank/datamodel/v1/dtos/getcustomer.py
bank/datamodel/v1/dtos/getcustomeraccounts.py
bank/datamodel/v1/dtos/registeruser.py
bank/datamodel/v1/dtos/transfer.py
bank/datamodel/v1/dtos/user.py
bank/datamodel/v1/dtos/views/__init__.py
bank/datamodel/v1/dtos/views/accountsview.py
bank/datamodel/v1/dtos/views/base.py
bank/datamodel/v1/dtos/views/customersview.py
bank/datamodel/v1/dtos/views/transfersview.py
bank/datamodel/v1/dtos/views/usersview.py
bank/protocol/__init__.py
bank/protocol/message.py
satsur_banking_api-0.0.4.dist-info/METADATA
satsur_banking_api-0.0.4.dist-info/WHEEL
satsur_banking_api-0.0.4.dist-info/top_level.txt
satsur_banking_api-0.0.4.dist-info/RECORD
