Metadata-Version: 2.4
Name: satsur-banking-api
Version: 0.0.4
Summary: Banking api and datamodel
Author-email: Satish Suryanarayan <satsur@gmail.com>
Classifier: Programming Language :: Python :: 3
Classifier: Operating System :: OS Independent
Requires-Python: >=3.13.0
Requires-Dist: email-validator>=2.2.0
Requires-Dist: pydantic>=2.11.7
